docdetect/__init__.py
docdetect/canny_edges.py
docdetect/hough_lines.py
docdetect/intersections.py
docdetect/line_utils.py
docdetect/processor.py
docdetect/quadrilaterals.py
docdetect-2019.1.2.dist-info/LICENSE
docdetect-2019.1.2.dist-info/METADATA
docdetect-2019.1.2.dist-info/WHEEL
docdetect-2019.1.2.dist-info/top_level.txt
docdetect-2019.1.2.dist-info/zip-safe
docdetect-2019.1.2.dist-info/RECORD
